Metadata-Version: 1.0
Name: zoopla-scraper-test
Version: 0.0.1
Summary: Test package that scrapes zoopla
Home-page: UNKNOWN
Author: Ivan Ying
Author-email: UNKNOWN
License: UNKNOWN
Platform: UNKNOWN
